{
  "projectId": "2405347",
  "projectName": "Thomas Wilfong",
  "updatedAt": "2026-07-08T20:55:41.481Z",
  "uploadedDocumentIds": [
    "189642412",
    "194111499",
    "189350360",
    "190847598",
    "189350181",
    "189350103",
    "189350570",
    "191109496",
    "190249602",
    "191899099",
    "191319269",
    "191036418",
    "191045133",
    "190112901",
    "191870107",
    "191984530",
    "190848709",
    "193039076",
    "193609544",
    "196712002",
    "195791625",
    "193188986",
    "193796404",
    "189350453",
    "198075285",
    "198174016",
    "198203539",
    "197071421",
    "198174037",
    "198198240",
    "198280406",
    "201951998",
    "198203254",
    "208087417",
    "209575287",
    "210930356",
    "210107460",
    "210984336",
    "210984335",
    "198399912",
    "189246492",
    "189642417",
    "189246497",
    "198203661",
    "189300920",
    "193796402",
    "189303940",
    "206270929",
    "189300679",
    "189642415",
    "189300785",
    "205989125",
    "204552069",
    "189303930",
    "189300782",
    "205989123",
    "189302102",
    "206271875",
    "198203308",
    "206665098",
    "206660329",
    "189300781",
    "198203318",
    "194581319",
    "189300776",
    "194133198",
    "190167357",
    "210981336",
    "210918629",
    "189355542",
    "210918626",
    "198962223",
    "198277501",
    "189303945",
    "196712815",
    "198203309",
    "189246490",
    "192104831",
    "190596526",
    "197871703",
    "194581309",
    "194484337",
    "194581936",
    "209715385",
    "189300543",
    "198203310",
    "194580401",
    "197868961",
    "189303936",
    "198239051",
    "193036749",
    "198240279",
    "189312835",
    "189314418",
    "189312525",
    "189310677",
    "193058242",
    "209845143",
    "189300929",
    "209845134",
    "198239052",
    "198240269",
    "198277656",
    "197137237",
    "197871698",
    "198961792",
    "189301105",
    "193796401",
    "189422917",
    "198203311",
    "210254243",
    "189308289",
    "210917912",
    "208693000",
    "198198222",
    "210107459",
    "208693001",
    "205426893",
    "194301742",
    "194133182",
    "198203312",
    "194131111"
  ],
  "uploadedFilenames": [
    "2025-03-31 Progressive-Veritas(1).pdf",
    "2025-03-06 Spine & Injury Lien.pdf",
    "2025-03-26 Veritas-USAA LOR.pdf",
    "2025-04-09 USAA-Veritas (MedPay ck $272.46).pdf",
    "2025-03-26 Veritas-Progressive LOR.pdf",
    "2025-03-26 Welcome Ltr to Client.pdf",
    "2025-03-26 Veritas-Meridian.pdf",
    "2025-04-11 USAA-Veritas (MedPay ck $184.92).pdf",
    "2025-04-09 USAA-Veritas.pdf",
    "2025-04-25 USAA-Veritas (Medpay ck $92.46).pdf",
    "2025-04-23 Veritas-Spine & Injury (Medpay $184.92).pdf",
    "2025-04-18 Veritas-Spine & Injury Ctr (Medpay ck $272.46).pdf",
    "2025-04-11 USAA-Veritas EOR.pdf",
    "2025-03-31 Progressive-Veritas.pdf",
    "2025-05-01 Carelon-Veritas.pdf",
    "2025-04-25 USAA-Veritas EOR.pdf",
    "2025-04-09 USAA-Veritas EOR.pdf",
    "2025-05-19 USAA-Veritas (medpay ledger).pdf",
    "2025-05-21 USAA-Veritas.pdf",
    "2025-07-07 Fax Cover Sheet-FHW Primary Care.pdf",
    "2025-06-24 USAA-Veritas.pdf",
    "2025-05-13 USAA-Veritas EOR.pdf",
    "2025-05-28 Progressive-Veritas (policy limits info).eml",
    "2025-03-26 Veritas-Carelon.pdf",
    "2025-07-14 USAA-Veritas.pdf",
    "2025-07-23 Billing Summary.pdf",
    "2025-07-09 USAA-Veritas EOR.pdf",
    "2025-07-23 Billing Summary.xlsx",
    "2025-07-23 Chronology.pdf",
    "2025-07-24 E Wilfong Thomas- CO DMV.pdf",
    "2025-09-03 USAA-Veritas.pdf",
    "2025-07-23 Wilfong Chrono.pdf",
    "2025-12-1 USAA-Veritas (permission to settle).pdf",
    "2025-12-10 USAA-Veritas.pdf",
    "2026-01-06 Progressive-Veritas(liab settlemnt $10558.00).pdf",
    "2025-12-30 Carelon Final.eml",
    "2026-01-14 Disbursement Statement.pdf",
    "2026-01-15 Veritas-Carelon.pdf",
    "27a07171-22c4-4dce-8d17-84e121b1fbbd.jpg",
    "34137392-28c8-477e-aef7-b8b0bdc0d841.jpg",
    "25-455547002_3-25-2025_Liability_General.pdf",
    "45475571-ed34-40c1-985e-81375f7eb704.jpg",
    "2025-11-7_Veritas (DEMAND Thomas Wilfong).docx",
    "Arctrieval HIPAA.pdf",
    "9611DCO + 4884 + A294 CO + A331 + A264.pdf",
    "Arctrieval HIPAA-Signed 2025-03-26 20-21-30.pdf",
    "ATS 000001.pdf",
    "Attorney Fee Agreement (Veritas) 2025-03-26 1358.docx",
    "25-455547002_3-25-2025_Photos - Property_Customer Photo.pdf",
    "Attorney Fee Agreement (Veritas) 2025-03-26 Wilfong.pdf",
    "b5b14c8c-eab5-4df9-82a5-6baacffc9b68.jpg",
    "Attorney Fee Agreement (Veritas) 2025-03-26 Wilfong-Signed 2025-03-26 20-21-30.pdf",
    "bcbs front.jpg",
    "B-ATS 000001.pdf",
    "BCBS back.jpg",
    "B-FHW 000001-000003 RFP.pdf",
    "2025-11-07_Veritas_USAA_Progressive (DEMAND).pdf",
    "client dl.jpg",
    "B-Spine & Injury Ctr of GJ 000001-000003 RFP.pdf",
    "B-FHW 000001-000003.pdf",
    "client pic.jpg",
    "B-Spine & Injury Ctr of GJ 000001-000003.pdf",
    "Conf_Fax_2025-03-26 Veritas-USAA LOR_2025-04-08-0827-PDT.pdf",
    "Disbursement Lien Letter 2026-01-15 0851.docx",
    "Disbursement Statement-Verification 2026-01-14 19-21-47.pdf",
    "Conf_Fax_2025-03-26 Veritas-Progressive LOR_2025-03-27-0853-PDT.pdf",
    "Disbursement Statement 2026-01-14 19-21-47.pdf",
    "DMV Report 000001.png.pdf",
    "DR 2478 Driver Record Requestor Release and Affidavit of Intended Use.pdf",
    "Fee Agreement and HIPAA-Verification 2025-03-26 20-21-30.pdf",
    "Fax_Fax Cover Sheet-FHW Primary Care_2025-07-07-0947-PDT.pdf",
    "B-FHW Primary Care 000001-000007 RFP.pdf",
    "f211831e-2468-49d2-885e-9e9c3b42c239.jpg",
    "FHW Billing Statement.jpg",
    "2025-04-03 USAA-Veritas (Copy of Policy).pdf",
    "B-FHW Primary Care 000001-000007.pdf",
    "FHW 000001-000005.pdf",
    "FHW Rehab Therapy.PDF",
    "FHW Rehab Therapy 000001-000001 No Records.pdf",
    "Full Release of all Claims-Tom Wilfong.pdf",
    "HIPAA Release 2025-03-26 1356.docx",
    "FHW 000001-000005 RFP.pdf",
    "FHW bills & recs.pdf",
    "FHW Primary Care bills & recs.pdf",
    "HIPAA Release 2025-03-26 1356-Signed 2025-03-26 20-21-30.pdf",
    "image0.png",
    "Impact Statement Template (2).pdf",
    "LOR Health Insurance 2025-03-26 1515.docx",
    "LOR Health Insurance 2025-03-26 1528.docx",
    "LOR Liability Insurance 2025-03-26 1513.docx",
    "LOR UIMBI Medpay Insurance 2025-03-26 1501.docx",
    "Policy Limits Request- Wilfong Thomas.pdf",
    "Progressive Release-Verification 2025-12-29 23-02-32.pdf",
    "Progressive insurance card.jpg",
    "Progressive Release 2025-12-29 23-02-32.pdf",
    "Proof of online accident report submission.eml",
    "Request for Collision Report.png",
    "T. Wilfong.eml",
    "FHW Primary Care 000001-000018.pdf",
    "Photos 000001-000003.pdf",
    "USAA card.png",
    "Thomas Wilfong vs. Progressive Direct Insurance Company.pdf",
    "USAA Claim.png",
    "FHW Primary Care 000001-000018 RFP.pdf",
    "Veritas Disbursement Sheet 2026-01-05 1531.xlsx",
    "Welcome letter to client 2025-03-26 1450.docx",
    "Wilfong Disbursement Statement.pdf",
    "Wilfong ADL.docx",
    "Wilfong Chrono.doc",
    "Wilfong item(1).pdf",
    "Wilfong item.pdf",
    "Wilfong Psychotherapy Letter.pdf",
    "Wilfong Impact Statement and Receipts.pdf",
    "Spine & Injury Ctr of GJ 000001-000041.pdf",
    "Spine & Injury Ctr of GJ 000001-000041 RFP.pdf",
    "Spine & Injury Ctr of GJ bills & records & lien.pdf"
  ]
}