{
  "projectId": "2267790",
  "projectName": "Ronald Hocker (Med Mal)",
  "updatedAt": "2026-07-09T00:54:25.262Z",
  "uploadedDocumentIds": [
    "178937853",
    "186446924",
    "186165883",
    "186248459",
    "186514392",
    "190846727",
    "190896789",
    "186333228",
    "186339490",
    "191403977",
    "187404839",
    "210080670",
    "191615853",
    "191404055",
    "192291875",
    "192173740",
    "192203456",
    "193030253",
    "193197149",
    "186487651",
    "193002567",
    "187987479",
    "207370116",
    "189075855",
    "208505051",
    "209984362",
    "201953285",
    "201596107",
    "198102846",
    "218557708",
    "196394536",
    "178358670",
    "190719531",
    "190694823",
    "196039041",
    "196039042",
    "191564911",
    "197364294",
    "196039053",
    "193031759",
    "192107267",
    "193030163",
    "196039046",
    "192107429",
    "191209288",
    "196039049",
    "196039044",
    "193710168",
    "192915352",
    "201595516",
    "196039058",
    "193326605",
    "193749239",
    "177304368",
    "178520182",
    "178520190",
    "190150536",
    "178987539",
    "194584060",
    "177362526",
    "177099577",
    "186331757",
    "178358669",
    "201595370",
    "191564338",
    "196038911",
    "191564902",
    "178358692",
    "192319592",
    "180561917",
    "196038915",
    "192220115",
    "196038928",
    "192219599",
    "191209239",
    "191192888",
    "196039057",
    "190500204",
    "201595107",
    "223167232",
    "191193881",
    "191373673",
    "187156794",
    "192915346",
    "192914825",
    "178935875",
    "196038927",
    "196038929",
    "193326594",
    "193325050",
    "196038930",
    "201595675",
    "187156103",
    "187156788"
  ],
  "uploadedFilenames": [
    "2024-11-21 Veritas-Client (welcome).pdf",
    "2025-02-18 SMH paid inv-Ronald Hocker.pdf",
    "2025-02-12 Veritas-Montrose Regional Health MRL.docx",
    "2025-02-12 Veritas-Montrose Reg Health (Cert mail).pdf",
    "2025-02-18 E Hocker Ronald- CIOX.pdf",
    "2025-04-11 E Hocker Ronald- Billing Solutions.pdf",
    "2025-04-17 MRO-MMH processing request.pdf",
    "2025-02-14 Veritas-Medicare LOR.pdf",
    "2025-02-13 Veritas-Montrose Reg Health (signed cert green card).pdf",
    "2025-04-23 E Hocker Ronald- ChartSwap (CO West).pdf",
    "2025-02-26 CMS-Veritas.pdf",
    "2024-02-12 Veritas-Montrose Regional Health (Candor)(1).pdf",
    "2025-04-28 E Hocker Ronald- ChartSwap (CO West).pdf",
    "2025-04-23 E Hocker Ronald- ChartSwap (WCRA).pdf",
    "2025-05-06 E Hocker Ronald- MRO.pdf",
    "2025-05-05 E Hocker Ronald- ChartSwap (WCRA).pdf",
    "2025-05-06 MRO invoice for MMH to pay.pdf",
    "2025-05-16 E Hocker Ronald- Motion Sense.pdf",
    "2025-05-19 E Hocker Ronald- MRO.pdf",
    "2024-02-12 Veritas-Montrose Regional Health (Candor).pdf",
    "2025-05-19 MRO-MMH invoice.pdf",
    "2025-03-05 CMS-Veritas.pdf",
    "2025-11-18 Veritas-MMH.docx",
    "2025-03-21 CMS-Veritas.pdf",
    "2025-12-04 Veritas-Montrose Regional.pdf",
    "2025-12-23 Veritas-Montrose Reg Health.pdf",
    "2025-09-05 CMS-Veritas.pdf",
    "2025-09-03 Veritas- Ronald Hocker Demand .doc",
    "2025-07-22 Veritas- Ronald Hocker Demand MRL.doc",
    "2026-04-13 Cert Ret Receipt (Montrose Reg Health-Sarah Abbott.pdf",
    "2025-07-18 Veritas- Ronald Hocker Demand (1st Draft).doc",
    "Arctrieval.pdf",
    "B-ACWC 000001-000004.pdf",
    "B-Anesthesia Consultants.pdf",
    "B-ACWC 000001-000004 RFP.pdf",
    "B-CO W ER Phys 000001-000003 RFP.pdf",
    "B-CO W ER Phys 000001-000003.pdf",
    "2025-07-14 Hocker-Veritas pictures.pdf",
    "B-MMH RFP.pdf",
    "B-MMH.pdf",
    "B-Mtn Radiology.pdf",
    "B-Mtn Radiology 000001 RFP.pdf",
    "B-Mtn Radiology 000001-000001.pdf",
    "B-Olathe Fire 000001-000003.pdf",
    "B-Motion Sense Therapy 000001-000003 RFP.pdf",
    "B-Olathe Fire 000001-000003 RFP.pdf",
    "Chronological_Medical_Record_Chart_Format (1).docx",
    "B-Motion Sense Therapy 000001-000003.pdf",
    "Chronological_Medical_Record_Chart_Format (1).pdf",
    "B-Uncompahgre Med Ctr 000001-000005 RFP.pdf",
    "B-Uncompahgre Med Ctr 000001-000005.pdf",
    "cocounsel_timeline_2025_05_29_no_fns.docx",
    "Fee agreement Candor or litigation.docx",
    "Fee Agreement 2024-11-15 19-52-54.pdf",
    "Fee Agreement-Verification 2024-11-15 19-52-54.pdf",
    "Fall demand Example.pdf",
    "Fee Agreement 2024-11-15 19-52-54(1).pdf",
    "Fall demand Example(1).pdf",
    "HIPAA Release 2024-10-29 1457.docx",
    "HITECH Release.docx",
    "LOR Health Insurance 2025-02-14 1433.docx",
    "HIPAA.pdf",
    "Medical Treatment Chronology.pdf",
    "CO W ER Phys bills & recs.pdf",
    "CO W ER Phys 000001-000060 RFP.pdf",
    "CO W ER Phys 000001-000060.pdf",
    "Montrose HIPAA.pdf",
    "MRO-MMH notice of processing.pdf",
    "Montrose Memorial Hospital (CP).pdf",
    "MMH 000001-000059 RFP.pdf",
    "MMH 000001-000059.pdf",
    "Olathe Fire 000001-000007 RFP.pdf",
    "MMH.pdf",
    "Olathe Fire 000001-000007.pdf",
    "Olathe Fire bills & recs.pdf",
    "B-SMH 000001-000034 RFP.pdf",
    "Olathe Fire invoice.pdf",
    "PRIVILEGE LOG- Ronald Hocker.pdf",
    "RE_ Hocker.eml",
    "Ron DL.jpg",
    "SEA 55 Falls 4 26 16 FINAL 2 Combined.pdf",
    "B-SMH 000001-000034.pdf",
    "Motion Sense Therapy 000001-000078.pdf",
    "Motion Sense Therapy bills & recs.pdf",
    "Welcome letter to client 2024-11-21 1518.docx",
    "SMH 000001-001127 Privileged.pdf",
    "Motion Sense Therapy 000001-000078 RFP.pdf",
    "Uncompahgre Med Ctr 000001-000014.pdf",
    "Uncompahgre Med Ctr bills & records.pdf",
    "Uncompahgre Med Ctr 000001-000014 RFP.pdf",
    "Ronald Hocker Demand- Veritas- 2025-09-03.pdf",
    "SMH bills & recs.pdf",
    "SMH 000001-001127.pdf"
  ]
}