{
  "projectId": "671074",
  "projectName": "Brandon Long (W.C.)",
  "updatedAt": "2026-07-09T08:01:37.123Z",
  "uploadedDocumentIds": [
    "47284099",
    "40334956",
    "53217566",
    "47675940",
    "50122762",
    "52443615",
    "53910986",
    "53910991",
    "30044412",
    "40655921",
    "52998766",
    "60986429",
    "58097019",
    "34380772",
    "40659414",
    "39989978",
    "38868173",
    "41457630",
    "40659440",
    "53032363",
    "53050488",
    "34380758",
    "53050041",
    "58088306",
    "64290781",
    "61757812",
    "54212895",
    "61864043",
    "61080114",
    "61863560",
    "61925042",
    "64993918",
    "66330069",
    "65785226",
    "66644136",
    "52443616",
    "61117514",
    "52443614",
    "52443618",
    "64340322",
    "38641796",
    "64340415",
    "52443623",
    "53007050",
    "53006758",
    "53006761",
    "53007048",
    "53007049",
    "47676948",
    "47676342",
    "47676958",
    "47676345",
    "47676344",
    "47676954",
    "60032451",
    "52443617",
    "54059459",
    "54059599",
    "52443622",
    "50122710",
    "34722850",
    "28386757",
    "61117512",
    "34127126",
    "28359012",
    "34803202",
    "34721735",
    "53006760",
    "54059610",
    "34722853",
    "34722787",
    "34722852",
    "34722779",
    "40406875",
    "34722784",
    "34722757",
    "34722756",
    "34722855",
    "34722857",
    "34722755",
    "34722860",
    "38076536",
    "38146743",
    "60986431",
    "34737948",
    "28359013",
    "53071432",
    "53910987",
    "34722836",
    "34722754",
    "38141124",
    "47675534",
    "34722753",
    "34722840",
    "34722758",
    "34722839",
    "34722772",
    "34722767",
    "34722838",
    "34722835",
    "34722776",
    "34722837",
    "34722777",
    "53050507",
    "34722842"
  ],
  "uploadedFilenames": [
    "04201183.pdf",
    "04196335.pdf",
    "04242888.pdf",
    "04201183(1).pdf",
    "04233709.pdf",
    "09bce4ca-dbd0-4c3a-9006-00a6a7b232b2.jpg",
    "04247952.pdf",
    "2023-06-07 L Doehling to Dr. Price (Enclosing IME for Rebuttal-Schedule Telephone Conference Call).docx",
    "2022-04-05 IME - Rascbacher.pdf",
    "2022-10-04 MA HIPAA.pdf",
    "2023.10.10 Stlmt Docs to CA - Long (04276671x9DD46).pdf",
    "04255358.pdf",
    "2023-06-15 L Doehling to Dr. Price (Request Rebuttal Report).pdf",
    "2023-07-27 Objection to FAL and DIME Req..docx",
    "2023-07-13 L St. Marys Occupational Med-Doehling(Dr. Olsen opinion).pdf",
    "2023-06-27 FAL Sedgwick-Doehling.pdf",
    "2023-07-27 Objection to FAL and DIME Req_.pdf",
    "2023-07-27 Objection to FAL and DIME Req..pdf",
    "2023-08-31 DIME Physician Panel.pdf",
    "2023-09-01 DIME Strike (1).pdf",
    "2023-09-01 DIME Strike.pdf",
    "2023-09-26 DRAFT Motion to Hold DIME.docx",
    "2023-10-11 WC Settlement Agreement (Signed)(1).pdf",
    "2023-10-17 Notice of Reschedule of DIME.docx",
    "2023-09-14 L Sedgwick-Doehling.pdf",
    "2023-10-19 Scheduled DIME Notification(1).docx",
    "2023-10-11 WC Settlement Agreement (Signed).pdf",
    "2023-10-19 Scheduled DIME Notification.docx",
    "2023-10-19 Scheduled DIME Notification.pdf",
    "2023-11-03 Ck Moore Ortho-Doehling (refund DIME $1150.00).pdf",
    "2023-11-20 DRAFT Disbursement Statement.docx",
    "2023-11-06 ck Sedgwick-Client (Lump Sum settlement $20000).pdf",
    "2023-11-20 WC Disbursement Statement.pdf",
    "2d64ab99-e11b-4a25-8e03-656957c59485.jpg",
    "5-168-674 - Late DIME Appointment - Brandon Long.eml",
    "a53d8778-3c6b-4bde-9a94-c8b5804e90ac.jpg",
    "595837ed-4768-400d-8513-479f47201ed9.jpg",
    "5-168-674 Brandon T. Long STC ORD 11.2.2023.pdf",
    "Attachments.html",
    "b686bdbe-9ee2-4ce5-ae9e-c94fa6d1829a.jpg",
    "Brandon Long 6.20.2023 LSB.pdf",
    "Brandon Long 64520 Auth Request Sedgwick 8.23.2023.pdf",
    "Brandon Long 7.26.2023.pdf",
    "Brandon Long attorney letter.pdf",
    "Brandon Long email correspondence.pdf",
    "Brandon Long Pain Specialists visit 7-6-2023.pdf",
    "Brandon Long.eml",
    "c74cac29-cb3a-4166-8b4f-ab4cb023646f.jpg",
    "Confirmation and Invoice merge_5168674.PDF",
    "d28dfcc3-527d-4e55-9b4a-04849d667e02.jpg",
    "DIME Flyer.pdf",
    "Community Hospital 000001-000141.pdf",
    "DIME Notice and Proposal (CP).pdf",
    "DIME-Report.PDF",
    "DRAFT Amended N P-DIME App - Long_claimant additions.docx",
    "Dr. Shaq Report (CP).pdf",
    "DRAFT Amended N P-DIME App - Long_claimant additions_208bd163vUL605vuzK7lVTCkSf3kGwaV1vVC (1).docx",
    "DRAFT Amended N P-DIME App - Long_claimant additions_208bd163vUL605vuzK7lVTCkSf3kGwaV1vVC.docx",
    "Confirmation and Invoice merge_5168674(1).PDF",
    "EXP-Hyzy 000001-000148.pdf",
    "EXP-Baldessari 000001-000107.pdf",
    "Fee Agreement (WC)(Executed).pdf",
    "FHWPS 000001-000060.pdf",
    "Grand Valley Ortho. 000001-000074.pdf",
    "Hanger Clinic 000001-000016.pdf",
    "Olsen Impairment Rating Report.pdf",
    "Olsen questionnaire.PDF",
    "RE_ Brandon Long(1).eml",
    "RE_ Brandon Long_ DIME application.eml",
    "RE_ Brandon Long DIME.eml",
    "Re_ WC 5-168-674.eml",
    "RE_ Brandon Long.eml",
    "RIRM 000001-000030.pdf",
    "RE_ Brandon Long_ DIME application follow up.eml",
    "RS3 Letter denying MRI request.pdf",
    "RIRM 000001-000055.pdf",
    "Rocky Mountain Rehab. Assoc. 000001-000038.pdf",
    "St. Marys Occupational 000001-000074.pdf",
    "St. Marys Life Center 000001-000024.pdf",
    "UBMC 000001-000026.pdf",
    "VA 000001-000662.pdf",
    "WC 5-168-674.pdf"
  ]
}