{
  "projectId": "225990",
  "projectName": "Matthew Sandler",
  "updatedAt": "2026-07-09T14:55:17.069Z",
  "failed": [
    {
      "documentId": "155978500",
      "filename": "Screenshot 2024-06-01 at 12.53.47?PM.jpeg",
      "folderName": "Matthew Sandler",
      "error": "Failed to download file from presigned URL (status: n/a): ENOENT: no such file or directory, open 'C:\\Users\\tomi\\Documents\\Projects\\FileVine Integration\\downloads\\Matthew Sandler_225990\\Screenshot 2024-06-01 at 12.53.47?PM.jpeg'",
      "firstFailedAt": "2026-07-09T14:55:17.068Z",
      "lastFailedAt": "2026-07-09T14:55:17.068Z"
    },
    {
      "documentId": "155978528",
      "filename": "Screenshot 2024-06-01 at 12.53.47?PM.jpeg",
      "folderName": "Matthew Sandler",
      "error": "Failed to download file from presigned URL (status: n/a): ENOENT: no such file or directory, open 'C:\\Users\\tomi\\Documents\\Projects\\FileVine Integration\\downloads\\Matthew Sandler_225990\\Screenshot 2024-06-01 at 12.53.47?PM.jpeg'",
      "firstFailedAt": "2026-07-09T14:55:17.033Z",
      "lastFailedAt": "2026-07-09T14:55:17.033Z"
    }
  ]
}